{
  "core-linux_headless64": [
    {
      "from": "0.12.10",
      "to": "0.12.11"
    },
    {
      "from": "0.12.11",
      "to": "0.12.12"
    },
    {
      "from": "0.12.12",
      "to": "0.12.13"
    },
    {
      "from": "0.12.13",
      "to": "0.12.14"
    },
    {
      "from": "0.12.14",
      "to": "0.12.15"
    },
    {
      "from": "0.12.15",
      "to": "0.12.16"
    },
    {
      "from": "0.12.16",
      "to": "0.12.17"
    },
    {
      "from": "0.12.17",
      "to": "0.12.18"
    },
    {
      "from": "0.12.18",
      "to": "0.12.19"
    },
    {
      "from": "0.12.19",
      "to": "0.12.20"
    },
    {
      "from": "0.12.20",
      "to": "0.12.21"
    },
    {
      "from": "0.12.21",
      "to": "0.12.22"
    },
    {
      "from": "0.12.22",
      "to": "0.12.23"
    },
    {
      "from": "0.12.23",
      "to": "0.12.24"
    },
    {
      "from": "0.12.24",
      "to": "0.12.25"
    },
    {
      "from": "0.12.25",
      "to": "0.12.26"
    },
    {
      "from": "0.12.26",
      "to": "0.12.27"
    },
    {
      "from": "0.12.27",
      "to": "0.12.28"
    },
    {
      "from": "0.12.28",
      "to": "0.12.29"
    },
    {
      "from": "0.12.29",
      "to": "0.12.30"
    },
    {
      "from": "0.12.30",
      "to": "0.12.31"
    },
    {
      "from": "0.12.31",
      "to": "0.12.32"
    },
    {
      "from": "0.12.32",
      "to": "0.12.33"
    },
    {
      "from": "0.12.33",
      "to": "0.12.34"
    },
    {
      "from": "0.12.34",
      "to": "0.12.35"
    },
    {
      "from": "0.12.35",
      "to": "0.13.0"
    },
    {
      "from": "0.12.7",
      "to": "0.12.8"
    },
    {
      "from": "0.12.8",
      "to": "0.12.9"
    },
    {
      "from": "0.12.9",
      "to": "0.12.10"
    },
    {
      "from": "0.13.0",
      "to": "0.13.1"
    },
    {
      "from": "0.13.1",
      "to": "0.13.2"
    },
    {
      "from": "0.13.10",
      "to": "0.13.11"
    },
    {
      "from": "0.13.11",
      "to": "0.13.12"
    },
    {
      "from": "0.13.12",
      "to": "0.13.13"
    },
    {
      "from": "0.13.13",
      "to": "0.13.14"
    },
    {
      "from": "0.13.14",
      "to": "0.13.15"
    },
    {
      "from": "0.13.15",
      "to": "0.13.16"
    },
    {
      "from": "0.13.16",
      "to": "0.13.17"
    },
    {
      "from": "0.13.17",
      "to": "0.13.18"
    },
    {
      "from": "0.13.18",
      "to": "0.13.19"
    },
    {
      "from": "0.13.18",
      "to": "0.14.0"
    },
    {
      "from": "0.13.19",
      "to": "0.13.20"
    },
    {
      "from": "0.13.2",
      "to": "0.13.3"
    },
    {
      "from": "0.13.3",
      "to": "0.13.4"
    },
    {
      "from": "0.13.4",
      "to": "0.13.5"
    },
    {
      "from": "0.13.5",
      "to": "0.13.6"
    },
    {
      "from": "0.13.6",
      "to": "0.13.7"
    },
    {
      "from": "0.13.7",
      "to": "0.13.8"
    },
    {
      "from": "0.13.8",
      "to": "0.13.9"
    },
    {
      "from": "0.13.9",
      "to": "0.13.10"
    },
    {
      "from": "0.14.0",
      "to": "0.14.1"
    },
    {
      "from": "0.14.1",
      "to": "0.14.2"
    },
    {
      "from": "0.14.10",
      "to": "0.14.11"
    },
    {
      "from": "0.14.11",
      "to": "0.14.12"
    },
    {
      "from": "0.14.12",
      "to": "0.14.13"
    },
    {
      "from": "0.14.13",
      "to": "0.14.14"
    },
    {
      "from": "0.14.14",
      "to": "0.14.15"
    },
    {
      "from": "0.14.15",
      "to": "0.14.16"
    },
    {
      "from": "0.14.16",
      "to": "0.14.17"
    },
    {
      "from": "0.14.17",
      "to": "0.14.18"
    },
    {
      "from": "0.14.18",
      "to": "0.14.19"
    },
    {
      "from": "0.14.19",
      "to": "0.14.20"
    },
    {
      "from": "0.14.2",
      "to": "0.14.3"
    },
    {
      "from": "0.14.20",
      "to": "0.14.21"
    },
    {
      "from": "0.14.21",
      "to": "0.14.22"
    },
    {
      "from": "0.14.22",
      "to": "0.14.23"
    },
    {
      "from": "0.14.23",
      "to": "0.15.1"
    },
    {
      "from": "0.14.3",
      "to": "0.14.4"
    },
    {
      "from": "0.14.4",
      "to": "0.14.5"
    },
    {
      "from": "0.14.5",
      "to": "0.14.6"
    },
    {
      "from": "0.14.6",
      "to": "0.14.7"
    },
    {
      "from": "0.14.7",
      "to": "0.14.8"
    },
    {
      "from": "0.14.8",
      "to": "0.14.9"
    },
    {
      "from": "0.14.9",
      "to": "0.14.10"
    },
    {
      "from": "0.15.0",
      "to": "0.15.1"
    },
    {
      "from": "0.15.1",
      "to": "0.15.2"
    },
    {
      "from": "0.15.10",
      "to": "0.15.11"
    },
    {
      "from": "0.15.11",
      "to": "0.15.12"
    },
    {
      "from": "0.15.12",
      "to": "0.15.13"
    },
    {
      "from": "0.15.13",
      "to": "0.15.14"
    },
    {
      "from": "0.15.14",
      "to": "0.15.15"
    },
    {
      "from": "0.15.15",
      "to": "0.15.16"
    },
    {
      "from": "0.15.16",
      "to": "0.15.17"
    },
    {
      "from": "0.15.17",
      "to": "0.15.18"
    },
    {
      "from": "0.15.18",
      "to": "0.15.19"
    },
    {
      "from": "0.15.19",
      "to": "0.15.20"
    },
    {
      "from": "0.15.2",
      "to": "0.15.3"
    },
    {
      "from": "0.15.20",
      "to": "0.15.21"
    },
    {
      "from": "0.15.21",
      "to": "0.15.22"
    },
    {
      "from": "0.15.22",
      "to": "0.15.23"
    },
    {
      "from": "0.15.23",
      "to": "0.15.24"
    },
    {
      "from": "0.15.24",
      "to": "0.15.25"
    },
    {
      "from": "0.15.25",
      "to": "0.15.26"
    },
    {
      "from": "0.15.26",
      "to": "0.15.27"
    },
    {
      "from": "0.15.27",
      "to": "0.15.28"
    },
    {
      "from": "0.15.28",
      "to": "0.15.29"
    },
    {
      "from": "0.15.29",
      "to": "0.15.30"
    },
    {
      "from": "0.15.3",
      "to": "0.15.4"
    },
    {
      "from": "0.15.30",
      "to": "0.15.31"
    },
    {
      "from": "0.15.31",
      "to": "0.15.32"
    },
    {
      "from": "0.15.32",
      "to": "0.15.33"
    },
    {
      "from": "0.15.33",
      "to": "0.15.34"
    },
    {
      "from": "0.15.34",
      "to": "0.15.35"
    },
    {
      "from": "0.15.35",
      "to": "0.15.36"
    },
    {
      "from": "0.15.36",
      "to": "0.15.37"
    },
    {
      "from": "0.15.37",
      "to": "0.15.38"
    },
    {
      "from": "0.15.38",
      "to": "0.15.39"
    },
    {
      "from": "0.15.39",
      "to": "0.15.40"
    },
    {
      "from": "0.15.4",
      "to": "0.15.5"
    },
    {
      "from": "0.15.40",
      "to": "0.16.36"
    },
    {
      "from": "0.15.5",
      "to": "0.15.6"
    },
    {
      "from": "0.15.6",
      "to": "0.15.7"
    },
    {
      "from": "0.15.7",
      "to": "0.15.8"
    },
    {
      "from": "0.15.8",
      "to": "0.15.9"
    },
    {
      "from": "0.15.9",
      "to": "0.15.10"
    },
    {
      "from": "0.16.0",
      "to": "0.16.1"
    },
    {
      "from": "0.16.1",
      "to": "0.16.2"
    },
    {
      "from": "0.16.10",
      "to": "0.16.11"
    },
    {
      "from": "0.16.11",
      "to": "0.16.12"
    },
    {
      "from": "0.16.12",
      "to": "0.16.13"
    },
    {
      "from": "0.16.13",
      "to": "0.16.14"
    },
    {
      "from": "0.16.14",
      "to": "0.16.15"
    },
    {
      "from": "0.16.15",
      "to": "0.16.16"
    },
    {
      "from": "0.16.16",
      "to": "0.16.17"
    },
    {
      "from": "0.16.17",
      "to": "0.16.18"
    },
    {
      "from": "0.16.18",
      "to": "0.16.19"
    },
    {
      "from": "0.16.19",
      "to": "0.16.20"
    },
    {
      "from": "0.16.2",
      "to": "0.16.3"
    },
    {
      "from": "0.16.20",
      "to": "0.16.21"
    },
    {
      "from": "0.16.21",
      "to": "0.16.22"
    },
    {
      "from": "0.16.22",
      "to": "0.16.23"
    },
    {
      "from": "0.16.23",
      "to": "0.16.24"
    },
    {
      "from": "0.16.24",
      "to": "0.16.25"
    },
    {
      "from": "0.16.25",
      "to": "0.16.26"
    },
    {
      "from": "0.16.26",
      "to": "0.16.27"
    },
    {
      "from": "0.16.27",
      "to": "0.16.28"
    },
    {
      "from": "0.16.28",
      "to": "0.16.29"
    },
    {
      "from": "0.16.29",
      "to": "0.16.30"
    },
    {
      "from": "0.16.3",
      "to": "0.16.4"
    },
    {
      "from": "0.16.30",
      "to": "0.16.31"
    },
    {
      "from": "0.16.31",
      "to": "0.16.32"
    },
    {
      "from": "0.16.32",
      "to": "0.16.33"
    },
    {
      "from": "0.16.33",
      "to": "0.16.34"
    },
    {
      "from": "0.16.34",
      "to": "0.16.35"
    },
    {
      "from": "0.16.35",
      "to": "0.16.36"
    },
    {
      "from": "0.16.36",
      "to": "0.16.37"
    },
    {
      "from": "0.16.37",
      "to": "0.16.38"
    },
    {
      "from": "0.16.38",
      "to": "0.16.39"
    },
    {
      "from": "0.16.39",
      "to": "0.16.40"
    },
    {
      "from": "0.16.4",
      "to": "0.16.5"
    },
    {
      "from": "0.16.40",
      "to": "0.16.41"
    },
    {
      "from": "0.16.41",
      "to": "0.16.42"
    },
    {
      "from": "0.16.42",
      "to": "0.16.43"
    },
    {
      "from": "0.16.43",
      "to": "0.16.44"
    },
    {
      "from": "0.16.44",
      "to": "0.16.45"
    },
    {
      "from": "0.16.45",
      "to": "0.16.46"
    },
    {
      "from": "0.16.46",
      "to": "0.16.47"
    },
    {
      "from": "0.16.47",
      "to": "0.16.48"
    },
    {
      "from": "0.16.48",
      "to": "0.16.49"
    },
    {
      "from": "0.16.49",
      "to": "0.16.50"
    },
    {
      "from": "0.16.5",
      "to": "0.16.6"
    },
    {
      "from": "0.16.50",
      "to": "0.16.51"
    },
    {
      "from": "0.16.51",
      "to": "0.16.6"
    },
    {
      "from": "0.16.6",
      "to": "0.16.7"
    },
    {
      "from": "0.16.7",
      "to": "0.16.8"
    },
    {
      "from": "0.16.8",
      "to": "0.16.9"
    },
    {
      "from": "0.16.9",
      "to": "0.16.10"
    },
    {
      "from": "0.17.10",
      "to": "0.17.11"
    },
    {
      "from": "0.17.11",
      "to": "0.17.12"
    },
    {
      "from": "0.17.12",
      "to": "0.17.13"
    },
    {
      "from": "0.17.13",
      "to": "0.17.14"
    },
    {
      "from": "0.17.14",
      "to": "0.17.15"
    },
    {
      "from": "0.17.15",
      "to": "0.17.16"
    },
    {
      "from": "0.17.16",
      "to": "0.17.17"
    },
    {
      "from": "0.17.17",
      "to": "0.17.18"
    },
    {
      "from": "0.17.18",
      "to": "0.17.19"
    },
    {
      "from": "0.17.19",
      "to": "0.17.20"
    },
    {
      "from": "0.17.20",
      "to": "0.17.21"
    },
    {
      "from": "0.17.21",
      "to": "0.17.22"
    },
    {
      "from": "0.17.22",
      "to": "0.17.23"
    },
    {
      "from": "0.17.23",
      "to": "0.17.24"
    },
    {
      "from": "0.17.24",
      "to": "0.17.25"
    },
    {
      "from": "0.17.25",
      "to": "0.17.26"
    },
    {
      "from": "0.17.26",
      "to": "0.17.27"
    },
    {
      "from": "0.17.27",
      "to": "0.17.28"
    },
    {
      "from": "0.17.28",
      "to": "0.17.29"
    },
    {
      "from": "0.17.29",
      "to": "0.17.30"
    },
    {
      "from": "0.17.30",
      "to": "0.17.31"
    },
    {
      "from": "0.17.31",
      "to": "0.17.32"
    },
    {
      "from": "0.17.32",
      "to": "0.17.33"
    },
    {
      "from": "0.17.33",
      "to": "0.17.34"
    },
    {
      "from": "0.17.34",
      "to": "0.17.35"
    },
    {
      "from": "0.17.35",
      "to": "0.17.36"
    },
    {
      "from": "0.17.36",
      "to": "0.17.37"
    },
    {
      "from": "0.17.37",
      "to": "0.17.38"
    },
    {
      "from": "0.17.38",
      "to": "0.17.39"
    },
    {
      "from": "0.17.39",
      "to": "0.17.40"
    },
    {
      "from": "0.17.40",
      "to": "0.17.41"
    },
    {
      "from": "0.17.41",
      "to": "0.17.42"
    },
    {
      "from": "0.17.42",
      "to": "0.17.43"
    },
    {
      "from": "0.17.43",
      "to": "0.17.44"
    },
    {
      "from": "0.17.44",
      "to": "0.17.45"
    },
    {
      "from": "0.17.45",
      "to": "0.17.46"
    },
    {
      "from": "0.17.46",
      "to": "0.17.47"
    },
    {
      "from": "0.17.47",
      "to": "0.17.48"
    },
    {
      "from": "0.17.48",
      "to": "0.17.49"
    },
    {
      "from": "0.17.49",
      "to": "0.17.50"
    },
    {
      "from": "0.17.50",
      "to": "0.17.51"
    },
    {
      "from": "0.17.51",
      "to": "0.17.52"
    },
    {
      "from": "0.17.52",
      "to": "0.17.53"
    },
    {
      "from": "0.17.53",
      "to": "0.17.54"
    },
    {
      "from": "0.17.54",
      "to": "0.17.55"
    },
    {
      "from": "0.17.55",
      "to": "0.17.56"
    },
    {
      "from": "0.17.56",
      "to": "0.17.57"
    },
    {
      "from": "0.17.57",
      "to": "0.17.58"
    },
    {
      "from": "0.17.58",
      "to": "0.17.59"
    },
    {
      "from": "0.17.59",
      "to": "0.17.60"
    },
    {
      "from": "0.17.60",
      "to": "0.17.61"
    },
    {
      "from": "0.17.61",
      "to": "0.17.62"
    },
    {
      "from": "0.17.62",
      "to": "0.17.63"
    },
    {
      "from": "0.17.63",
      "to": "0.17.64"
    },
    {
      "from": "0.17.64",
      "to": "0.17.65"
    },
    {
      "from": "0.17.65",
      "to": "0.17.66"
    },
    {
      "from": "0.17.66",
      "to": "0.17.67"
    },
    {
      "from": "0.17.67",
      "to": "0.17.68"
    },
    {
      "from": "0.17.68",
      "to": "0.17.69"
    },
    {
      "from": "0.17.7",
      "to": "0.17.8"
    },
    {
      "from": "0.17.8",
      "to": "0.17.9"
    },
    {
      "from": "0.17.9",
      "to": "0.17.10"
    },
    {
      "stable": "0.17.69"
    }
  ]
}
